mbrola/__about___.py
mbrola/__init__.py
mbrola/mbrola.py
mbrola/py.typed
mbrola-0.2.0.dist-info/licenses/LICENSE
mbrola-0.2.0.dist-info/METADATA
mbrola-0.2.0.dist-info/WHEEL
mbrola-0.2.0.dist-info/top_level.txt
mbrola-0.2.0.dist-info/RECORD
