Metadata-Version: 2.4
Name: mbrola
Version: 0.2.0
Summary: A Python front-end for the MBROLA speech synthesizer
Author-email: Gonzalo Garcia-Castro <gongarciacastro@gmail.com>
License-Expression: MIT
Project-URL: Documentation, https://github.com/gongcastro/pymbrola#readme
Project-URL: Issues, https://github.com/gongcastro/pymbrola/issues
Project-URL: Source, https://github.com/gongcastro/pymbrola
Classifier: Development Status :: 4 - Beta
Classifier: Programming Language :: Python
Classifier: Programming Language :: Python :: 3.8
Classifier: Programming Language :: Python :: 3.9
Classifier: Programming Language :: Python :: 3.10
Classifier: Programming Language :: Python :: 3.11
Classifier: Programming Language :: Python :: 3.12
Classifier: Programming Language :: Python :: Implementation :: CPython
Classifier: Programming Language :: Python :: Implementation :: PyPy
Requires-Python: >=3.12
License-File: LICENSE
Requires-Dist: pytest>=8.3.5
Dynamic: license-file
